ynm_shengwu_mcp_12138/__init__.py
ynm_shengwu_mcp_12138-0.1.1.dist-info/METADATA
ynm_shengwu_mcp_12138-0.1.1.dist-info/WHEEL
ynm_shengwu_mcp_12138-0.1.1.dist-info/entry_points.txt
ynm_shengwu_mcp_12138-0.1.1.dist-info/RECORD
