Metadata-Version: 2.4
Name: ynm-shengwu-mcp-12138
Version: 0.1.1
Summary: 一个用于查询和管理学生生物错题的MCP插件
Author-email: Waller-Man <2935256635@qq.com>
Requires-Python: >=3.12
Requires-Dist: mcp[cli]>=1.10.1
Requires-Dist: openpyxl
Requires-Dist: pandas
